moonlightpy/__init__.py
moonlightpy/__main__.py
moonlightpy/client.py
moonlightpy/coding.py
moonlightpy/com.py
moonlightpy/logger.py
moonlightpy/msg.py
moonlightpy/server.py
moonlightpy/util.py
moonlightpy-0.0.13.dist-info/METADATA
moonlightpy-0.0.13.dist-info/WHEEL
moonlightpy-0.0.13.dist-info/top_level.txt
moonlightpy-0.0.13.dist-info/RECORD
