Metadata-Version: 2.1
Name: moonlightpy
Version: 0.0.13
Summary: reverse port forwarding tool
Home-page: https://github.com/xitongsys/moonlight
Author: xitongsys
Author-email: xitongsys@gmail.com
License: UNKNOWN
Platform: UNKNOWN
